mdxcanvas/__init__.py
mdxcanvas/deploy/__init__.py
mdxcanvas/deploy/algorithms.py
mdxcanvas/deploy/announcement.py
mdxcanvas/deploy/assignment.py
mdxcanvas/deploy/canvas_deploy.py
mdxcanvas/deploy/checksums.py
mdxcanvas/deploy/course_settings.py
mdxcanvas/deploy/file.py
mdxcanvas/deploy/group.py
mdxcanvas/deploy/migration.py
mdxcanvas/deploy/module.py
mdxcanvas/deploy/override.py
mdxcanvas/deploy/page.py
mdxcanvas/deploy/quiz.py
mdxcanvas/deploy/syllabus.py
mdxcanvas/deploy/util.py
mdxcanvas/deploy/zip.py
mdxcanvas/deployment_report.py
mdxcanvas/erasecanvas/__init__.py
mdxcanvas/erasecanvas/main.py
mdxcanvas/error_helpers.py
mdxcanvas/extensions.py
mdxcanvas/main.py
mdxcanvas/our_logging.py
mdxcanvas/processing_context.py
mdxcanvas/resources.py
mdxcanvas/text_processing/__init__.py
mdxcanvas/text_processing/inline_math.py
mdxcanvas/text_processing/jinja_processing.py
mdxcanvas/text_processing/markdown_processing.py
mdxcanvas/util.py
mdxcanvas/xml_processing/__init__.py
mdxcanvas/xml_processing/announcement_tags.py
mdxcanvas/xml_processing/assignment_tags.py
mdxcanvas/xml_processing/attributes.py
mdxcanvas/xml_processing/group_tags.py
mdxcanvas/xml_processing/inline_styling.py
mdxcanvas/xml_processing/module_tags.py
mdxcanvas/xml_processing/override_parsing.py
mdxcanvas/xml_processing/page_tags.py
mdxcanvas/xml_processing/quiz_questions.py
mdxcanvas/xml_processing/quiz_tags.py
mdxcanvas/xml_processing/syllabus_tags.py
mdxcanvas/xml_processing/tag_preprocessors.py
mdxcanvas/xml_processing/xml_processing.py
mdxcanvas-0.6.5.dist-info/METADATA
mdxcanvas-0.6.5.dist-info/WHEEL
mdxcanvas-0.6.5.dist-info/entry_points.txt
mdxcanvas-0.6.5.dist-info/licenses/LICENSE
mdxcanvas-0.6.5.dist-info/RECORD
