Metadata-Version: 2.4
Name: mdxcanvas
Version: 0.6.5
Summary: A Canvas LMS API wrapper for maintaining content in markdown
License: MIT
License-File: LICENSE
Author: Gordon Bean
Author-email: gbean@cs.byu.edu
Requires-Python: >=3.10,<4.0
Classifier: License :: OSI Approved :: MIT License
Classifier: Programming Language :: Python :: 3
Classifier: Programming Language :: Python :: 3.10
Classifier: Programming Language :: Python :: 3.11
Classifier: Programming Language :: Python :: 3.12
Classifier: Programming Language :: Python :: 3.13
Classifier: Programming Language :: Python :: 3.14
Requires-Dist: CanvasAPI (>=3.2.0,<4.0.0)
Requires-Dist: Jinja2 (>=3.1.2,<4.0.0)
Requires-Dist: Markdown (>=3.1.1,<4.0.0)
Requires-Dist: MarkupSafe (>=2.0.1,<3.0.0)
Requires-Dist: Pygments (>=2.17.2,<3.0.0)
Requires-Dist: beautifulsoup4 (>=4.13.4,<5.0.0)
Requires-Dist: cssutils (>=2.11.1,<3.0.0)
Requires-Dist: markdowndata (>=0.1.0,<0.2.0)
Requires-Dist: pymdown-extensions (>=10.16.1,<11.0.0)
Requires-Dist: pytest (>=8.4.0,<9.0.0)
Requires-Dist: pytz (>=2025.2,<2026.0)
Requires-Dist: pyyaml (>=6.0.2,<7.0.0)
Requires-Dist: strictyaml (>=1.7.3,<2.0.0)
